{"user":[{"_id":2,"_username":"raul","_email":"raul@gmail.com","_password":"$2b$10$coxATVJJ87fxTOcerq2.hOrfW7.CYYIu99EM.0hkRmb50q4rt3jDe"},{"_id":3,"_username":"lucia","_email":"lucia@gmail.com","_password":"$2b$10$e10UR/stb7nD7EXf3O8JG.fAUDNjywDZovuV4ok1nhPpWrG6ph5Ha"}],"song":[{"_id":1,"_title":"song1","_uri":"www.song1.com","_duration":"2","_image":"www.imagen.com","_idArtist":1,"_idGenero":3},{"_id":3,"_title":"song3","_uri":"www.song3.com","_duration":"2","_image":"www.imagen.com","_idArtist":1,"_idGenero":3},{"_id":4,"_title":"song4","_uri":"www.song4.com","_duration":"2","_image":"www.imagen.com","_idArtist":1,"_idGenero":3}],"playlist":[]}